{
"version" : "test",
"keys":
{
"anim":   "Animal - Животные",
"basic":  "Basic - Базовый набор слов",
"bird":   "Birds - Птицы",
"body":   "Body - Тело",
"clo":    "Clothes - Одежда",
"col":    "Colors - Цвета",
"food":   "Food - Еда",
"insec":  "Insects - Насекомые"
},
"words":
[
{
"eng":"arm",
"key":"body|basic",
"tra":"",
"itr":"",
"rus":"рука"
},
{
"eng":"back",
"key":"body|basic",
"tra":"",
"itr":"",
"rus":"спина"
},
{
"eng":"belly button",
"key":"body",
"tra":"",
"itr":"",
"rus":"пуп"
},
{
"eng":"big toe",
"key":"body",
"tra":"",
"itr":"",
"rus":"большой палец ноги"
},
{
"eng":"chin",
"key":"body",
"tra":"",
"itr":"",
"rus":"подбородок"
},
{
"eng":"double chin",
"key":"body",
"tra":"",
"itr":"",
"rus":"двойной подбородок"
},
{
"eng":"ear",
"key":"body",
"tra":"",
"itr":"",
"rus":"ухо"
},
{
"eng":"elbow",
"key":"body",
"tra":"",
"itr":"",
"rus":"локоть"
},
{
"eng":"eye",
"key":"body",
"tra":"",
"itr":"",
"rus":"глаз"
},
{
"eng":"eyebrow",
"key":"body",
"tra":"",
"itr":"",
"rus":"бровь"
},
{
"eng":"finger",
"key":"body",
"tra":"",
"itr":"",
"rus":"палец (руки, один из 4х)"
},
{
"eng":"foot",
"key":"body|basic",
"tra":"",
"itr":"",
"rus":"ступня, стопа"
},
{
"eng":"forehead",
"key":"body",
"tra":"",
"itr":"",
"rus":"лоб"
},
{
"eng":"hair",
"key":"body|basic",
"tra":"",
"itr":"",
"rus":"волосы"
},
{
"eng":"hand",
"key":"body",
"tra":"",
"itr":"",
"rus":"кисть руки"
},
{
"eng":"head",
"key":"body",
"itr":"hed",
"rus":"голова; глава, руководитель(ница)"
},
{
"eng":"heel",
"key":"body",
"tra":"",
"itr":"",
"rus":"пятка"
},
{
"eng":"hip",
"key":"body",
"tra":"",
"itr":"",
"rus":"бедро"
},
{
"eng":"knee",
"key":"body",
"tra":"",
"itr":"",
"rus":"колено"
},
{
"eng":"knees|lap",
"key":"body",
"tra":"ни:с|лэп",
"rus":"колени"
},
{
"eng":"leg",
"key":"body|basic",
"tra":"",
"itr":"",
"rus":"нога"
},
{
"eng":"mouth",
"key":"body",
"tra":"",
"itr":"",
"rus":"рот"
},
{
"eng":"neck",
"key":"body",
"tra":"",
"itr":"",
"rus":"шея"
},
{
"eng":"nose",
"key":"body|basic",
"tra":"",
"itr":"",
"rus":"нос"
},
{
"eng":"shoulder",
"key":"body",
"tra":"",
"itr":"",
"rus":"плечо"
},
{
"eng":"stomach",
"key":"body",
"tra":"",
"itr":"",
"rus":"живот"
},
{
"eng":"tooth",
"key":"body|basic",
"tra":"",
"itr":"",
"rus":"зуб"
},
{
"eng":"mustache",
"key":"body",
"tra":"маста'ж",
"rus":"усы, ус"
},
{
"eng":"book",
"key":"basic",
"tra":"",
"itr":"",
"rus":"книга"
},
{
"eng":"brush",
"key":"basic",
"tra":"",
"itr":"",
"rus":"щетка, кисточка"
},
{
"eng":"chair",
"key":"basic",
"tra":"",
"itr":"",
"rus":"стул"
},
{
"eng":"door",
"key":"basic",
"tra":"",
"itr":"",
"rus":"дверь"
},
{
"eng":"pen",
"key":"basic",
"tra":"",
"itr":"",
"rus":"ручка"
},
{
"eng":"pencil",
"key":"basic",
"tra":"",
"itr":"",
"rus":"карандаш"
},
{
"eng":"picture",
"key":"basic",
"tra":"",
"itr":"",
"rus":"картина"
},
{
"eng":"table",
"key":"basic",
"tra":"",
"itr":"",
"rus":"стол"
},
{
"eng":"wall",
"key":"basic",
"tra":"",
"itr":"",
"rus":"стена"
},
{
"eng":"window",
"key":"basic",
"tra":"",
"itr":"",
"rus":"окно"
},
{
"eng":"my",
"key":"basic",
"tra":"",
"itr":"",
"rus":"мой, моя, моё, мои"
},
{
"eng":"he",
"key":"basic",
"tra":"",
"itr":"",
"rus":"он"
},
{
"eng":"she",
"key":"basic",
"tra":"",
"itr":"",
"rus":"она"
},
{
"eng":"you",
"key":"basic",
"tra":"",
"itr":"",
"rus":"ты, Вы, вы"
},
{
"eng":"we",
"key":"basic",
"tra":"",
"itr":"",
"rus":"мы"
},
{
"eng":"they",
"key":"basic",
"tra":"",
"itr":"",
"rus":"они"
},
{
"eng":"baby",
"key":"basic",
"tra":"",
"itr":"",
"rus":"младенец"
},
{
"eng":"boy",
"key":"basic",
"tra":"",
"itr":"",
"rus":"мальчик"
},
{
"eng":"child",
"key":"basic",
"tra":"",
"itr":"",
"rus":"ребенок"
},
{
"eng":"children",
"key":"basic",
"tra":"",
"itr":"",
"rus":"дети"
},
{
"eng":"friend",
"key":"basic",
"tra":"",
"itr":"",
"rus":"друг"
},
{
"eng":"girl",
"key":"basic",
"tra":"",
"itr":"",
"rus":"девочка"
},
{
"eng":"big",
"key":"basic",
"tra":"биг",
"rus":"большой"
},
{
"eng":"small",
"key":"basic",
"tra":"смол",
"rus":"маленький (s...)"
},
{
"eng":"little",
"key":"basic",
"tra":"литл",
"itr":"",
"rus":"маленький (l...)"
},
{
"eng":"color",
"key":"col|basic",
"tra":"",
"itr":"",
"rus":"цвет"
},
{
"eng":"black and white",
"key":"col",
"tra":"",
"itr":"",
"rus":"черно-белый"
},
{
"eng":"black",
"key":"col|basic",
"tra":"",
"itr":"",
"rus":"черный"
},
{
"eng":"blue",
"key":"col|basic",
"tra":"",
"itr":"",
"rus":"голубой, синий"
},
{
"eng":"brown",
"key":"col",
"tra":"",
"itr":"",
"rus":"коричневый"
},
{
"eng":"dark",
"key":"col",
"tra":"",
"itr":"",
"rus":"темно- (какой-то цвет)"
},
{
"eng":"gold",
"key":"col",
"tra":"",
"itr":"",
"rus":"золотой, золото"
},
{
"eng":"gray|grey",
"key":"col",
"tra":"грей",
"rus":"серый, седой"
},
{
"eng":"green",
"key":"col|basic",
"tra":"",
"itr":"",
"rus":"зеленый"
},
{
"eng":"lilac",
"key":"col",
"tra":"",
"itr":"",
"rus":"сиреневый, сирень"
},
{
"eng":"multicolored",
"key":"col",
"tra":"",
"itr":"",
"rus":"многоцветный, разноцветный"
},
{
"eng":"orange",
"key":"col",
"tra":"",
"itr":"",
"rus":"оранжевый"
},
{
"eng":"pink",
"key":"col",
"tra":"",
"itr":"",
"rus":"розовый, гвоздика"
},
{
"eng":"purple",
"key":"col",
"tra":"",
"itr":"",
"rus":"пурпурный, лиловый, багровый, фиолетовый (в т.ч.)"
},
{
"eng":"red",
"key":"col|basic",
"tra":"",
"itr":"",
"rus":"красный"
},
{
"eng":"silver",
"key":"col",
"tra":"",
"itr":"",
"rus":"серебряный, серебристый"
},
{
"eng":"violet",
"key":"col",
"tra":"",
"itr":"",
"rus":"фиолетовый, фиалка"
},
{
"eng":"white",
"key":"col|basic",
"tra":"",
"itr":"",
"rus":"белый"
},
{
"eng":"yellow",
"key":"col|basic",
"tra":"",
"itr":"",
"rus":"желтый"
},

{
"eng":"dress",
"key":"clo|basic",
"tra":"",
"itr":"",
"rus":"платье"
},
{
"eng":"hat",
"key":"clo|basic",
"tra":"",
"itr":"",
"rus":"шапка, шляпа"
},
{
"eng":"skirt",
"key":"clo|basic",
"tra":"скёрт",
"itr":"",
"rus":"юбка"
},
{
"eng":"socks",
"key":"clo",
"tra":"",
"itr":"",
"rus":"носки"
},
{
"eng":"suit",
"key":"clo",
"tra":"",
"itr":"",
"rus":"костюм"
},
{
"eng":"sweater",
"key":"clo",
"tra":"",
"itr":"",
"rus":"свитер"
},
{
"eng":"T-shirt",
"key":"clo",
"tra":"",
"itr":"",
"rus":"футболка"
},
{
"eng":"trousers",
"key":"clo",
"tra":"",
"itr":"",
"rus":"брюки"
},
{
"eng":"underwear",
"key":"clo",
"tra":"",
"itr":"",
"rus":"нижнее белье"
},
{
"eng":"watch",
"key":"clo",
"tra":"",
"itr":"",
"rus":"часы (наручные)"
},
{
"eng":"food",
"key":"food",
"tra":"",
"itr":"",
"rus":"еда, пища"
},
{
"eng":"breakfast",
"key":"food",
"tra":"",
"itr":"",
"rus":"завтрак"
},
{
"eng":"apple",
"key":"food|basic",
"tra":"",
"itr":"",
"rus":"яблоко"
},
{
"eng":"bacon",
"key":"food",
"tra":"",
"itr":"",
"rus":"бекон, почеревка"
},
{
"eng":"banana",
"key":"food|basic",
"tra":"",
"itr":"",
"rus":"банан"
},
{
"eng":"bread",
"key":"food",
"tra":"",
"itr":"",
"rus":"хлеб"
},
{
"eng":"butter",
"key":"food",
"tra":"",
"itr":"",
"rus":"масло (сливочное)"
},
{
"eng":"cheese",
"key":"food",
"tra":"",
"itr":"",
"rus":"сыр"
},
{
"eng":"coffee",
"key":"food",
"tra":"",
"itr":"",
"rus":"кофе"
},
{
"eng":"cookie",
"key":"food",
"tra":"",
"itr":"",
"rus":"печенька"
},
{
"eng":"cookies",
"key":"food",
"tra":"",
"itr":"",
"rus":"печенье"
},
{
"eng":"cornflakes",
"key":"food",
"tra":"",
"itr":"",
"rus":"кукурузные хлопья"
},
{
"eng":"egg",
"key":"food",
"tra":"",
"itr":"",
"rus":"яйцо (обычно куриное)"
},
{
"eng":"for breakfast",
"key":"food",
"tra":"",
"itr":"",
"rus":"на завтрак"
},
{
"eng":"for lunch",
"key":"food",
"tra":"",
"itr":"",
"rus":"на обед"
},
{
"eng":"for dinner",
"key":"food",
"tra":"",
"itr":"",
"rus":"на ужин"
},
{
"eng":"fruit",
"key":"food",
"tra":"",
"itr":"",
"rus":"фрукт"
},
{
"eng":"ham",
"key":"food",
"tra":"",
"itr":"",
"rus":"ветчина"
},
{
"eng":"hamburger",
"key":"food",
"tra":"",
"itr":"",
"rus":"бутерброд, гамбургер"
},
{
"eng":"have breakfast",
"key":"food",
"tra":"",
"itr":"",
"rus":"завтракать"
},
{
"eng":"have lunch",
"key":"food",
"tra":"",
"itr":"",
"rus":"обедать"
},
{
"eng":"have dinner",
"key":"food",
"tra":"",
"itr":"",
"rus":"ужинать"
},
{
"eng":"cook breakfast|make breakfast",
"key":"food",
"tra":"",
"itr":"",
"rus":"готовить завтракать"
},
{
"eng":"cook lunch|make lunch",
"key":"food",
"tra":"",
"itr":"",
"rus":"готовить обед"
},
{
"eng":"cook dinner|make dinner",
"key":"food",
"tra":"",
"itr":"",
"rus":"готовить ужин"
},
{
"eng":"jam",
"key":"food",
"tra":"",
"itr":"",
"rus":"варенье, джем"
},
{
"eng":"juice",
"key":"food",
"tra":"",
"itr":"",
"rus":"сок"
},
{
"eng":"marmalade",
"key":"food",
"tra":"",
"itr":"",
"rus":"мармелад"
},
{
"eng":"milk",
"key":"food|basic",
"tra":"",
"itr":"",
"rus":"молоко"
},
{
"eng":"oatmeal",
"key":"food",
"tra":"о'утми:л",
"itr":"ˈəutmiːl",
"rus":"овсяная крупа, овсянка"
},
{
"eng":"orange",
"key":"food",
"tra":"",
"itr":"",
"rus":"апельсин"
},
{
"eng":"roll",
"key":"food",
"tra":"",
"itr":"",
"rus":"булочка"
},
{
"eng":"salt",
"key":"food",
"tra":"",
"itr":"",
"rus":"соль"
},
{
"eng":"sausage",
"key":"food",
"tra":"со'сидж",
"itr":"ˈsɔsɪdʒ",
"rus":"колбаса, сосиска"
},
{
"eng":"sausages",
"key":"food",
"tra":"со'сиджис",
"itr":"ˈsɔsɪdʒɪs",
"rus":"сосиски"
},
{
"eng":"sugar",
"key":"food",
"tra":"",
"itr":"",
"rus":"сахар"
},
{
"eng":"tea",
"key":"food|basic",
"tra":"",
"itr":"",
"rus":"чай"
},
{
"eng":"toast",
"key":"food",
"tra":"",
"itr":"",
"rus":"тост (хлебный), гренка"
},
{
"eng":"water",
"key":"food|basic",
"tra":"",
"itr":"",
"rus":"вода"
},
{
"eng":"with",
"key":"food",
"tra":"",
"itr":"",
"rus":"с (чем-либо)"
},
{
"eng":"without",
"key":"food",
"tra":"",
"itr":"",
"rus":"без (чего-либо)"
},
{
"eng":"porrige",
"key":"food",
"tra":"по'ридж",
"itr":"ˈpɔrɪdʒ",
"rus":"каша, овсянка"
},
{
"eng":"lunch",
"key":"food|basic",
"tra":"ланч",
"rus":"обед"
},
{
"eng":"dinner",
"key":"food|basic",
"tra":"ди'неР",
"rus":"ужин"
},
{
"eng":"meat",
"key":"food",
"tra":"мит",
"rus":"мясо"
},
{
"eng":"vegetables",
"key":"food",
"tra":"веджетеблс",
"rus":"овощи"
},
{
"eng":"potatoes",
"key":"food",
"tra":"пете'йтес",
"rus":"картофель"
},
{
"eng":"rice",
"key":"food",
"tra":"райс",
"rus":"рис"
},
{
"eng":"French fries",
"key":"food",
"tra":"френч фрайс",
"rus":"картошка фри"
},
{
"eng":"soup",
"key":"food",
"tra":"суп",
"rus":"суп"
},
{
"eng":"pastа",
"key":"food",
"tra":"па'сте | пе'сте",
"rus":"макаронные изделия"
},
{
"eng":"pork",
"key":"food",
"tra":"пок",
"rus":"свинина"
},
{
"eng":"chicken",
"key":"food",
"tra":"чи'кен",
"rus":"курятина"
},
{
"eng":"beef",
"key":"food",
"tra":"би:ф",
"rus":"говядина"
},
{
"eng":"wine",
"key":"food",
"tra":"вайн",
"rus":"вино"
},
{
"eng":"beer",
"key":"food",
"tra":"биа",
"rus":"пиво"
},
{
"eng":"ice",
"key":"food",
"tra":"айс",
"rus":"лед"
},
{
"eng":"ice cream|ice-cream",
"key":"food",
"tra":"айс крим",
"rus":"мороженое"
},
{
"eng":"dairy products",
"key":"food",
"tra":"де'йри про'дактс",
"rus":"молочные продукты"
},
{
"eng":"seafood",
"key":"food",
"tra":"си'фуд",
"rus":"морепродукты"
},
{
"eng":"tasty",
"key":"food",
"tra":"тэ'йсти",
"rus":"вкусный"
},
{
"eng":"delicious",
"key":"food",
"tra":"дили'шес",
"rus":"деликатесный, очень вкусный, восхитительный"
},
{
"eng":"salty",
"key":"food",
"tra":"со'лти",
"rus":"соленый"
},
{
"eng":"bitter",
"key":"food",
"tra":"би'теР",
"rus":"горький"
},
{
"eng":"sweet",
"key":"food",
"tra":"сви:т",
"rus":"сладкий"
},
{
"eng":"sour",
"key":"food",
"tra":"са'уэ",
"rus":"кислый"
},
{
"eng":"full",
"key":"food",
"tra":"фул",
"rus":"сытый, наевшийся"
},
{
"eng":"hungry",
"key":"food",
"tra":"ха'нгРи",
"rus":"голодный"
},
{
"eng":"coke",
"key":"food",
"tra":"кеок",
"rus":"кола"
},
{
"eng":"biscuit",
"key":"food",
"tra":"би'сквит",
"rus":"бисквит"
},
{
"eng":"pie",
"key":"food",
"tra":"пай",
"rus":"пирог"
},
{
"eng":"chewing gum",
"key":"food",
"tra":"чуин гам",
"rus":"жевательная резинка"
},
{
"eng":"candy",
"key":"food",
"tra":"кэнди",
"rus":"конфета"
},
{
"eng":"lemon",
"key":"food",
"tra":"ле'мон",
"rus":"лемон"
},
{
"eng":"honey",
"key":"food",
"tra":"ха'ни",
"rus":"мед"
},
{
"eng":"chocolate",
"key":"food",
"tra":"чоклед",
"rus":"шоколад"
},
{
"eng":"chips",
"key":"food",
"tra":"чипс",
"rus":"чипсы"
},
{
"eng":"fish and chips",
"key":"food",
"tra":"",
"itr":"",
"rus":"рыбные палочки"
},
{
"eng":"yogurt",
"key":"food",
"tra":"йо'гурт",
"rus":"йогурт"
},
{
"eng":"nuts",
"key":"food",
"tra":"натс",
"rus":"орехи"
},
{
"eng":"animal",
"key":"anim",
"itr":"ˈænɪməl",
"tra":"э'нимел",
"rus":"животное"
},
{
"eng":"deer",
"key":"anim",
"tra":"",
"itr":"",
"rus":"олень"
},
{
"eng":"deer",
"key":"anim",
"tra":"",
"itr":"",
"rus":"олени"
},
{
"eng":"sheep",
"key":"anim",
"tra":"",
"itr":"",
"rus":"овца"
},
{
"eng":"sheep",
"key":"anim",
"tra":"",
"itr":"",
"rus":"овцы"
},
{
"eng":"fish",
"key":"anim",
"tra":"",
"itr":"",
"rus":"рыба"
},
{
"eng":"fish",
"key":"anim",
"tra":"",
"itr":"",
"rus":"рыбы"
},
{
"eng":"mouse",
"key":"anim",
"tra":"",
"itr":"",
"rus":"мышь"
},
{
"eng":"mice",
"key":"anim",
"tra":"",
"itr":"",
"rus":"мыши"
},
{
"eng":"snake",
"key":"anim",
"itr":"",
"tra":"снэйк",
"rus":"змея"
},
{
"eng":"dolphin",
"key":"anim",
"itr":"",
"tra":"до'лфин",
"rus":"дельфин"
},
{
"eng":"chick",
"key":"anim|bird",
"itr":"",
"tra":"чик",
"rus":"цыпленок"
},
{
"eng":"squirrel",
"key":"anim",
"itr":"",
"tra":"скви'рэл",
"rus":"белка"
},
{
"eng":"lion",
"key":"anim",
"itr":"",
"tra":"ла'йен",
"rus":"лев"
},
{
"eng":"bear",
"key":"anim",
"itr":"",
"tra":"бэ'аР",
"rus":"медведь"
},
{
"eng":"elephant",
"key":"anim",
"itr":"",
"tra":"э'лефент",
"rus":"слон"
},
{
"eng":"monkey",
"key":"anim",
"itr":"",
"tra":"ма'нки",
"rus":"обезьяна"
},
{
"eng":"donkey",
"key":"anim",
"itr":"",
"tra":"до'нки",
"rus":"осел"
},
{
"eng":"bird",
"key":"anim|bird|basic",
"itr":"",
"tra":"бёрд",
"rus":"птица"
},
{
"eng":"penguin",
"key":"anim",
"itr":"",
"tra":"пэ'нгвин",
"rus":"пингвин"
},
{
"eng":"tiger",
"key":"anim|basic",
"itr":"",
"tra":"та'йгер",
"rus":"тигр"
},
{
"eng":"turtle",
"key":"anim",
"itr":"",
"tra":"тётл",
"rus":"черепаха"
},
{
"eng":"pigeon",
"key":"anim|bird",
"itr":"",
"tra":"пи'джен",
"rus":"голубь (обычный, дворовой)"
},
{
"eng":"dove",
"key":"anim|bird",
"itr":"",
"tra":"дав",
"rus":"голубь (красивый, благородный)"
},
{
"eng":"cow",
"key":"anim|basic",
"itr":"",
"tra":"кау",
"rus":"корова"
},
{
"eng":"bull",
"key":"anim",
"itr":"",
"tra":"бул",
"rus":"бык"
},
{
"eng":"camel",
"key":"anim",
"itr":"",
"tra":"кэ'мэл",
"rus":"верблюд"
},
{
"eng":"wolf",
"key":"anim|basic",
"itr":"",
"tra":"вулф",
"rus":"волк"
},
{
"eng":"giraffe",
"key":"anim",
"itr":"",
"tra":"джира'ф",
"rus":"жираф"
},
{
"eng":"goat",
"key":"anim",
"itr":"",
"tra":"го'ут",
"rus":"козел, коза"
},
{
"eng":"bite",
"key":"anim|insec",
"itr":"",
"tra":"байт",
"rus":"кусать, укус"
},
{
"eng":"sting",
"key":"anim|insec",
"itr":"",
"tra":"стинГ",
"rus":"жалить, жало"
},
{
"eng":"pet",
"key":"anim",
"itr":"",
"tra":"",
"rus":"домашний любимец, питомец"
},
{
"eng":"pig",
"key":"anim|basic",
"itr":"",
"tra":"пиг",
"rus":"свинья"
},
{
"eng":"fox",
"key":"anim",
"itr":"",
"tra":"фокс",
"rus":"лиса"
},
{
"eng":"hen",
"key":"anim|bird",
"itr":"",
"tra":"",
"rus":"курица"
},
{
"eng":"cock",
"key":"anim|bird",
"itr":"",
"tra":"",
"rus":"петух"
},
{
"eng":"frog",
"key":"anim|basic",
"itr":"frɔg",
"tra":"фрог",
"rus":"лягушка"
},
{
"eng":"farm",
"key":"anim",
"tra":"фам",
"rus":"фермерские (животные)"
},
{
"eng":"domestic",
"key":"anim",
"itr":"",
"tra":"домэ'стик",
"rus":"домашние (животные)"
},
{
"eng":"wild",
"key":"anim",
"itr":"",
"tra":"вайлд",
"rus":"дикие (животные)"
},
{
"eng":"zoo",
"key":"anim|basic",
"itr":"",
"tra":"зу:",
"rus":"зоопарк"
},
{
"eng":"feed",
"key":"anim|food",
"tra":"",
"itr":"",
"rus":"кормить"
},
{
"eng":"duck",
"key":"anim|bird",
"tra":"",
"itr":"",
"rus":"утка"
},
{
"eng":"whiskers",
"key":"anim",
"tra":"",
"itr":"",
"rus":"усы (у животных)"
},
{
"eng":"insect",
"key":"anim|insec",
"itr":"ˈɪnsɛkt",
"tra":"и'нсект",
"rus":"насекомое"
},
{
"eng":"bee",
"key":"anim|insec|basic",
"itr":"",
"tra":"би:",
"rus":"пчела"
},
{
"eng":"ant",
"key":"anim|insec",
"itr":"",
"tra":"энт",
"rus":"муравей"
},
{
"eng":"falcon",
"key":"anim|bird",
"tra":"",
"itr":"",
"rus":"сокол"
},
{
"eng":"hawk",
"key":"anim|bird",
"tra":"",
"itr":"",
"rus":"ястреб"
},
{
"eng":"key",
"key":"basic",
"tra":"",
"itr":"",
"rus":"ключ"
},
{
"eng":"day",
"key":"basic",
"tra":"",
"itr":"",
"rus":"день"
},
{
"eng":"dollar",
"key":"basic",
"tra":"",
"itr":"",
"rus":"доллар"
},
{
"eng":"word",
"key":"basic",
"tra":"",
"itr":"",
"rus":"слово"
},
{
"eng":"list",
"key":"basic",
"tra":"",
"itr":"",
"rus":"список"
},
{
"eng":"goodbye|bye",
"key":"basic",
"tra":"",
"itr":"",
"rus":"до свидания"
},
{
"eng":"wrist",
"key":"body",
"tra":"рист",
"rus":"запястье"
},
{
"eng":"ankle",
"key":"body",
"tra":"энкл",
"rus":"лодыжка, щиколотка"
},
{
"eng":"cheek",
"key":"body",
"tra":"чи:к",
"itr":"tʃiːk",
"rus":"щека; наглость, дерзость"
},
{
"eng":"mammal",
"key":"anim",
"tra":"мэ'мал",
"itr":"",
"rus":"млекопитающее"
},
{
"eng":"whale",
"key":"anim",
"tra":"вэйл",
"itr":"",
"rus":"кит"
},
{
"eng":"soft drink",
"key":"food",
"tra":"",
"itr":"",
"rus":"безалкогольный напиток"
},
{
"eng":"song",
"key":"basic",
"tra":"сонГ",
"itr":"",
"rus":"песня"
},
{
"eng":"cafe|café",
"key":"food",
"tra":"кэ'фей",
"itr":"ˈkæfeɪ",
"rus":"кафе"
},
{
"eng":"shirt",
"key":"clo",
"tra":"шёРт",
"itr":"",
"rus":"рубашка"
},
{
"eng":"blouse",
"key":"clo",
"tra":"блаус",
"itr":"",
"rus":"блузка"
},
{
"eng":"swimsuit",
"key":"clo",
"tra":"свимсьют",
"itr":"",
"rus":"купальник"
},
{
"eng":"swim trunks",
"key":"clo",
"tra":"свим транкс",
"itr":"",
"rus":"плавки"
},
{
"eng":"trainers",
"key":"clo",
"tra":"трэйнерс",
"itr":"",
"rus":"кроссовки"
},
{
"eng":"cap",
"key":"clo",
"tra":"",
"itr":"",
"rus":"кепка, бейсболка"
},
{
"eng":"cockroach",
"key":"insec",
"itr":"ˈkɔkrəutʃ",
"tra":"ко'крач",
"rus":"таракан"
},
{
"eng":"wasp",
"key":"insec",
"itr":"wɒsp",
"tra":"восп",
"rus":"оса"
},
{
"eng":"mosquito",
"key":"insec",
"itr":"mɔsˈkiːtəu",
"tra":"моски'те",
"rus":"комар"
},
{
"eng":"bug|beetle",
"key":"insec",
"itr":"bʌg | ˈbiːtl",
"tra":"баг | битл",
"rus":"жук"
},
{
"eng":"aphid",
"key":"insec",
"itr":"ˈeɪfɪd",
"tra":"э'йфид",
"rus":"тля"
},
{
"eng":"spider",
"key":"insec",
"itr":"ˈspaɪdəʳ",
"tra":"спа'йдэР",
"rus":"паук"
},
{
"eng":"midge",
"key":"insec",
"itr":"mɪdʒ",
"tra":"мидж",
"rus":"мошка"
},
{
"eng":"dragonfly",
"key":"insec",
"itr":"ˈdrægənflaɪ",
"tra":"дрэ'генфлай",
"rus":"стрекоза"
},
{
"eng":"butterfly",
"key":"insec",
"itr":"ˈbʌtəflaɪ",
"tra":"ба'тефлай",
"rus":"бабочка"
},
{
"eng":"moth",
"key":"insec",
"itr":"mɔθ",
"tra":"мос",
"rus":"мотылёк"
},
{
"eng":"clothes moth",
"key":"insec",
"itr":"kləuðz mɔθ",
"tra":"клоузс мос",
"rus":"моль"
},
{
"eng":"grasshopper",
"key":"insec",
"itr":"ˈgrɑːsˌhɒpəʳ",
"tra":"грасхо'пеР",
"rus":"кузнечик"
},
{
"eng":"ladybug|ladybird",
"key":"insec",
"itr":"ˈleɪdɪbbʌg | ˈleɪdɪbəːd",
"tra":"",
"rus":"божья коровка (бр|ам)"
},
{
"eng":"locust",
"key":"insec",
"itr":"ˈləukəst",
"tra":"ло'кест",
"rus":"саранча"
},
{
"eng":"Colorado beetle",
"key":"insec",
"itr":"",
"tra":"колораде битл",
"rus":"колорадский жук"
},
{
"eng":"chafer",
"key":"insec",
"itr":"",
"tra":"че'йфа",
"rus":"майский жук"
},
{
"eng":"maggot",
"key":"insec",
"itr":"ˈmægət",
"tra":"мэ'гет",
"rus":"личинка"
},
{
"eng":"worm",
"key":"anim|basic",
"itr":"wəːm",
"tra":"во:м",
"rus":"червь"
},
{
"eng":"earthworm",
"key":"anim",
"itr":"ˈəːθwəːm",
"tra":"э'Рсво:м",
"rus":"земляной (дождевой) червь"
},
{
"eng":"caterpillar",
"key":"insec",
"itr":"ˈkætəpɪləʳ",
"tra":"ка'тепилаР",
"rus":"гусеница"
},
{
"eng":"fly",
"key":"insec",
"itr":"flaɪ",
"tra":"флай",
"rus":"муха"
}
]
}
